configerus/__init__.py
configerus/config.py
configerus/format.py
configerus/instances.py
configerus/loaded.py
configerus/plugin.py
configerus/shared.py
configerus/validator.py
configerus/contrib/dict/__init__.py
configerus/contrib/dict/source.py
configerus/contrib/env/__init__.py
configerus/contrib/env/env_json_source.py
configerus/contrib/env/env_specific_source.py
configerus/contrib/files/__init__.py
configerus/contrib/files/format.py
configerus/contrib/files/source.py
configerus/contrib/get/__init__.py
configerus/contrib/get/format.py
configerus/contrib/jsonschema/__init__.py
configerus/contrib/jsonschema/validate.py
configerus/test/__init__.py
configerus/test/test_1_load.py
configerus/test/test_1_shared.py
configerus/test/test_2_config_get_behaviour.py
configerus/test/test_3_config_copy.py
configerus/test/test_4_validate.py
configerus/test/test_5_templating.py
configerus/test/test_6_instances.py
configerus-3.0.1.dist-info/LICENSE
configerus-3.0.1.dist-info/METADATA
configerus-3.0.1.dist-info/WHEEL
configerus-3.0.1.dist-info/entry_points.txt
configerus-3.0.1.dist-info/top_level.txt
configerus-3.0.1.dist-info/RECORD
