Metadata-Version: 2.1
Name: configerus
Version: 3.0.1
Summary: Plugin-Based configuration manager
Home-page: https://github.com/james-nesbitt/configerus
Author: James Nesbitt
Author-email: james.r.nesbitt@gmail.com
License: MIT
Project-URL: Source, https://github.com/james-nesbitt/configerus
Keywords: test,unittest
Platform: unix
Platform: linux
Platform: osx
Classifier: Development Status :: 4 - Beta
Classifier: Intended Audience :: Developers
Classifier: License :: OSI Approved :: MIT License
Classifier: Operating System :: MacOS :: MacOS X
Classifier: Operating System :: POSIX
Classifier: Programming Language :: Python :: 3
Classifier: Programming Language :: Python :: 3 :: Only
Classifier: Programming Language :: Python :: 3.8
Classifier: Programming Language :: Python :: 3.9
Classifier: Topic :: Software Development :: Libraries
Classifier: Topic :: Utilities
License-File: LICENSE
Requires-Dist: pyyaml
Requires-Dist: jsonschema
